{
    "name": "Something Awful Smilies",
    "author": "Tempus Thales",
    "emotes": [
        {
            "name": "rory",
            "url": "https://fi.somethingawful.com/images/smilies/rainbow.gif"
        },
        {
            "name": "rznv",
            "url": "https://fi.somethingawful.com/safs/smilies/8/7/rznv.001.gif"
        },
        {
            "name": "shroom",
            "url": "https://i.somethingawful.com/forumsystem/emoticons/emot-shroom.gif"
        },
        {
            "name": "tinsley",
            "url": "https://fi.somethingawful.com/customtitles/eris/classic_fillmore.gif"
        },
        {
            "name": "weed",
            "url": "https://i.somethingawful.com/forumsystem/emoticons/emot-weed.gif"
        },
        {
            "name": "abrathink",
            "url": "https://fi.somethingawful.com/safs/smilies/f/6/abrathink.001.gif"
        },
        {
            "name": "abuela",
            "url": "https://fi.somethingawful.com/safs/smilies/8/4/abuela.001.png"
        },
        {
            "name": "acab",
            "url": "https://fi.somethingawful.com/safs/smilies/2/7/acab.001.png"
        },
        {
            "name": "agreed",
            "url": "https://fi.somethingawful.com/safs/smilies/b/b/agreed.001.png"
        },
        {
            "name": "alexa",
            "url": "https://fi.somethingawful.com/safs/smilies/c/c/alexa.001.gif"
        },
        {
            "name": "ali",
            "url": "https://fi.somethingawful.com/safs/smilies/d/b/ali.001.gif"
        },
        {
            "name": "aliexpress",
            "url": "https://fi.somethingawful.com/safs/smilies/a/2/aliexpress.001.gif"
        },
        {
            "name": "aronrex",
            "url": "https://fi.somethingawful.com/safs/smilies/0/f/aronrex.001.gif"
        },
        {
            "name": "atlus",
            "url": "https://fi.somethingawful.com/safs/smilies/b/b/atlus.001.gif"
        },
        {
            "name": "auspol",
            "url": "https://fi.somethingawful.com/safs/smilies/a/f/auspol.001.gif"
        },
        {
            "name": "baath",
            "url": "https://fi.somethingawful.com/safs/smilies/a/6/baath.001.gif"
        },
        {
            "name": "baduk",
            "url": "https://fi.somethingawful.com/safs/smilies/1/6/baduk.001.gif"
        },
        {
            "name": "bananacoin",
            "url": "https://fi.somethingawful.com/safs/smilies/6/b/bananacoin.001.gif"
        },
        {
            "name": "barry",
            "url": "https://fi.somethingawful.com/safs/smilies/d/2/barry.001.png"
        },
        {
            "name": "basta",
            "url": "https://fi.somethingawful.com/safs/smilies/0/0/basta.001.gif"
        },
        {
            "name": "bern101",
            "url": "https://fi.somethingawful.com/safs/smilies/9/c/bern101.001.gif"
        },
        {
            "name": "bernchloe",
            "url": "https://fi.somethingawful.com/safs/smilies/9/c/bernchloe.001.png"
        },
        {
            "name": "bernget20",
            "url": "https://fi.somethingawful.com/safs/smilies/c/3/bernget20.001.gif"
        },
        {
            "name": "berninator",
            "url": "https://fi.somethingawful.com/safs/smilies/2/1/berninator.001.gif"
        },
        {
            "name": "bernout",
            "url": "https://fi.somethingawful.com/safs/smilies/c/d/bernout.001.gif"
        },
        {
            "name": "bernpop",
            "url": "https://fi.somethingawful.com/safs/smilies/1/4/bernpop.001.gif"
        },
        {
            "name": "bgc",
            "url": "https://fi.somethingawful.com/safs/smilies/d/7/bgc.001.gif"
        },
        {
            "name": "biden",
            "url": "https://fi.somethingawful.com/safs/smilies/b/e/biden.001.png"
        },
        {
            "name": "blastback",
            "url": "https://fi.somethingawful.com/safs/smilies/5/8/blastback.001.gif"
        }
    ]
}